{"skeleton":{"hash":"UsZyLgHJtc8","spine":"3.8-from-4.0.17","x":-71.94,"y":-63.38,"width":147,"height":133,"images":"./images/","audio":"C:/Users/Admin/Desktop/icon game maya/icon ho"},"bones":[{"name":"root"},{"name":"ho","parent":"root","x":0.05,"y":0.89},{"name":"ho2","parent":"ho"}],"slots":[{"name":"Group 9","bone":"root","attachment":"Group 9"},{"name":"Layer 31 copy","bone":"ho","attachment":"Layer 31 copy"},{"name":"Layer 31 copy2","bone":"ho2","attachment":"Layer 31 copy","blend":"additive"}],"skins":[{"name":"default","attachments":{"Group 9":{"Group 9":{"x":2.06,"y":4.12,"width":138,"height":131}},"Layer 31 copy":{"Layer 31 copy":{"x":1.51,"y":2.23,"width":147,"height":133}},"Layer 31 copy2":{"Layer 31 copy":{"x":1.51,"y":2.23,"width":147,"height":133}}}}],"animations":{"active":{"slots":{"Layer 31 copy2":{"color":[{"color":"ffffff00","curve":"stepped"},{"time":0.2,"color":"ffffff00"},{"time":0.3333,"color":"ffffffab"},{"time":0.9333,"color":"ffffff00"}]}},"bones":{"ho2":{"scale":[{"time":0.3333},{"time":0.8,"x":1.303,"y":1.303}]},"ho":{"scale":[{},{"time":0.3333,"x":1.174,"y":1.174,"curve":"stepped"},{"time":1,"x":1.174,"y":1.174},{"time":1.3333}]}}},"unactive":{"slots":{"Group 9":{"color":[{"color":"9a9a9aff"}]},"Layer 31 copy":{"color":[{"color":"9a9a9aff"}]},"Layer 31 copy2":{"color":[{"color":"ffffff00"}]}}},"waiting":{"slots":{"Layer 31 copy2":{"color":[{"color":"ffffff00"}]}}}}}